canon_keeper_mcp/__init__.py
canon_keeper_mcp/__main__.py
canon_keeper_mcp/install.py
canon_keeper_mcp/server.py
canon_keeper_mcp-0.1.6.dist-info/METADATA
canon_keeper_mcp-0.1.6.dist-info/WHEEL
canon_keeper_mcp-0.1.6.dist-info/entry_points.txt
canon_keeper_mcp-0.1.6.dist-info/RECORD
