Metadata-Version: 2.4
Name: canon-keeper-mcp
Version: 0.1.6
Summary: MCP server for persisting learnings from Copilot conversations - no API key required
Project-URL: Homepage, https://github.com/phantom-man
Project-URL: Repository, https://github.com/phantom-man/canon_keeper_mcp
Project-URL: Documentation, https://github.com/phantom-man/canon_keeper_mcp/blob/main/README.md
Author-email: Phantom-man <damienfosborn@gmail.com>
License: MIT
Keywords: ai,copilot,github,mcp,memory,session
Classifier: Development Status :: 4 - Beta
Classifier: Intended Audience :: Developers
Classifier: License :: OSI Approved :: MIT License
Classifier: Programming Language :: Python :: 3
Classifier: Programming Language :: Python :: 3.10
Classifier: Programming Language :: Python :: 3.11
Classifier: Programming Language :: Python :: 3.12
Classifier: Topic :: Software Development :: Libraries :: Python Modules
Requires-Python: >=3.10
Requires-Dist: mcp>=1.0.0
